blackburn/__init__.py
blackburn-1.4.7.dist-info/LICENSE
blackburn-1.4.7.dist-info/METADATA
blackburn-1.4.7.dist-info/WHEEL
blackburn-1.4.7.dist-info/top_level.txt
blackburn-1.4.7.dist-info/RECORD
