Metadata-Version: 2.1
Name: blackburn
Version: 1.4.7
Summary: Common library for projects created by Github @BlackburnHax
Home-page: https://github.com/BlackburnHax/blackburn
Author: Brandon Blackburn
Author-email: contact@bhax.net
License: Apache License, Version 2.0
Platform: UNKNOWN
Classifier: License :: OSI Approved :: Apache Software License
Classifier: Operating System :: MacOS :: MacOS X
Classifier: Operating System :: Microsoft :: Windows
Classifier: Operating System :: POSIX
Classifier: Programming Language :: Python
Classifier: Programming Language :: Python :: 3
Classifier: Programming Language :: Python :: 3 :: Only
Classifier: Natural Language :: English
License-File: LICENSE
Requires-Dist: requests
Requires-Dist: bcrypt
Requires-Dist: mongoblack
Requires-Dist: humanize
Requires-Dist: pythonping
Requires-Dist: netaddr
